etc_jupyterlab_feedback/__init__.py
etc_jupyterlab_feedback/_version.py
etc_jupyterlab_feedback/application.py
etc_jupyterlab_feedback/handlers.py
etc_jupyterlab_feedback/labextension/build_log.json
etc_jupyterlab_feedback/labextension/package.json
etc_jupyterlab_feedback/labextension/schemas/@educational-technology-collective/etc_jupyterlab_feedback/package.json.orig
etc_jupyterlab_feedback/labextension/schemas/@educational-technology-collective/etc_jupyterlab_feedback/plugin.json
etc_jupyterlab_feedback/labextension/static/lib_index_js.706e3844fb1e47ea9e82.js
etc_jupyterlab_feedback/labextension/static/lib_index_js.706e3844fb1e47ea9e82.js.map
etc_jupyterlab_feedback/labextension/static/remoteEntry.b878dad288ae6ae43565.js
etc_jupyterlab_feedback/labextension/static/remoteEntry.b878dad288ae6ae43565.js.map
etc_jupyterlab_feedback/labextension/static/style.js
etc_jupyterlab_feedback/labextension/static/style_index_js.ab85a44818daaf520017.js
etc_jupyterlab_feedback/labextension/static/style_index_js.ab85a44818daaf520017.js.map
etc_jupyterlab_feedback/labextension/static/vendors-node_modules_css-loader_dist_runtime_api_js-node_modules_css-loader_dist_runtime_cssW-72eba1.f401fe20d789473d9301.js
etc_jupyterlab_feedback/labextension/static/vendors-node_modules_css-loader_dist_runtime_api_js-node_modules_css-loader_dist_runtime_cssW-72eba1.f401fe20d789473d9301.js.map
etc_jupyterlab_feedback-2.0.10.data/data/etc/jupyter/jupyter_notebook_config.d/etc_jupyterlab_feedback.json
etc_jupyterlab_feedback-2.0.10.data/data/etc/jupyter/jupyter_server_config.d/etc_jupyterlab_feedback.json
etc_jupyterlab_feedback-2.0.10.data/data/share/jupyter/labextensions/@educational-technology-collective/etc_jupyterlab_feedback/build_log.json
etc_jupyterlab_feedback-2.0.10.data/data/share/jupyter/labextensions/@educational-technology-collective/etc_jupyterlab_feedback/install.json
etc_jupyterlab_feedback-2.0.10.dist-info/LICENSE
etc_jupyterlab_feedback-2.0.10.dist-info/METADATA
etc_jupyterlab_feedback-2.0.10.dist-info/WHEEL
etc_jupyterlab_feedback-2.0.10.dist-info/top_level.txt
etc_jupyterlab_feedback-2.0.10.dist-info/RECORD
