Metadata-Version: 2.1
Name: etc-jupyterlab-feedback
Version: 2.0.10
Summary: A JupyterLab extension.
Home-page: https://github.com/educational-technology-collective/etc_jupyterlab_feedback
Author: ETC
Author-email: 
License: BSD-3-Clause
Keywords: Jupyter,JupyterLab,JupyterLab3
Platform: Linux
Platform: Mac OS X
Platform: Windows
Classifier: License :: OSI Approved :: BSD License
Classifier: Programming Language :: Python
Classifier: Programming Language :: Python :: 3
Classifier: Programming Language :: Python :: 3.7
Classifier: Programming Language :: Python :: 3.8
Classifier: Programming Language :: Python :: 3.9
Classifier: Programming Language :: Python :: 3.10
Classifier: Framework :: Jupyter
Classifier: Framework :: Jupyter :: JupyterLab
Classifier: Framework :: Jupyter :: JupyterLab :: 3
Classifier: Framework :: Jupyter :: JupyterLab :: Extensions
Classifier: Framework :: Jupyter :: JupyterLab :: Extensions :: Prebuilt
Requires-Python: >=3.7
License-File: LICENSE
Requires-Dist: jupyter-server (<2,>=1.6)
Provides-Extra: test
